chessboard_image/__init__.py
chessboard_image/_version.py
chessboard_image/cli.py
chessboard_image/generator.py
chessboard_image/theme.json
chessboard_image-1.1.3.dist-info/LICENSE
chessboard_image-1.1.3.dist-info/METADATA
chessboard_image-1.1.3.dist-info/WHEEL
chessboard_image-1.1.3.dist-info/entry_points.txt
chessboard_image-1.1.3.dist-info/top_level.txt
chessboard_image-1.1.3.dist-info/RECORD
