Metadata-Version: 2.1
Name: chessboard-image
Version: 1.1.3
Summary: Generate beautiful chess board images from FEN notation
Home-page: https://github.com/anandjoshi91/chessboard-image
Author: Anand Joshi
Author-email: Anand Joshi <anandhjoshi@outlook.com>
License: MIT
Project-URL: Homepage, https://github.com/anandjoshi91/chessboard-image
Project-URL: Documentation, https://github.com/anandjoshi91/chessboard-image#readme
Project-URL: Repository, https://github.com/anandjoshi91/chessboard-image.git
Project-URL: Bug Reports, https://github.com/anandjoshi91/chessboard-image/issues
Keywords: chess,fen,board,image,generator,diagram,visualization
Classifier: Development Status :: 5 - Production/Stable
Classifier: Intended Audience :: Developers
Classifier: Intended Audience :: End Users/Desktop
Classifier: Topic :: Games/Entertainment :: Board Games
Classifier: Topic :: Multimedia :: Graphics :: Graphics Conversion
Classifier: Topic :: Software Development :: Libraries :: Python Modules
Classifier: License :: OSI Approved :: MIT License
Classifier: Programming Language :: Python :: 3
Classifier: Programming Language :: Python :: 3.7
Classifier: Programming Language :: Python :: 3.8
Classifier: Programming Language :: Python :: 3.9
Classifier: Programming Language :: Python :: 3.10
Classifier: Programming Language :: Python :: 3.11
Classifier: Programming Language :: Python :: 3.12
Classifier: Operating System :: OS Independent
Requires-Python: >=3.7
License-File: LICENSE
Requires-Dist: Pillow >=8.0.0
Provides-Extra: dev
Requires-Dist: pytest >=6.0 ; extra == 'dev'
Requires-Dist: pytest-cov >=2.0 ; extra == 'dev'
Requires-Dist: black >=21.0 ; extra == 'dev'
Requires-Dist: flake8 >=3.8 ; extra == 'dev'
Requires-Dist: mypy >=0.800 ; extra == 'dev'
Provides-Extra: test
Requires-Dist: pytest >=6.0 ; extra == 'test'
Requires-Dist: pytest-cov >=2.0 ; extra == 'test'
